setup.cfg
setup.py
curlc/__init__.py
curlc/curlc.py
curlc.egg-info/PKG-INFO
curlc.egg-info/SOURCES.txt
curlc.egg-info/dependency_links.txt
curlc.egg-info/entry_points.txt
curlc.egg-info/requires.txt
curlc.egg-info/top_level.txt