Metadata-Version: 1.1
Name: curlc
Version: 0.0.3
Summary: curl wrapper to borrow cookies from your browser's authenticated session
Home-page: https://github.com/jb55/curlc
Author: William Casarin
Author-email: bill@casarin.me
License: GPLv2
Keywords: curlc
Platform: UNKNOWN
Classifier: Programming Language :: Python :: 3
Classifier: Environment :: Console
Classifier: Intended Audience :: Developers
Classifier: Intended Audience :: System Administrators
Classifier: Topic :: Internet :: WWW/HTTP
Classifier: Topic :: Software Development
Classifier: Topic :: System :: Networking
Classifier: Topic :: Terminals
Classifier: Topic :: Utilities
